llama_index/py.typed
llama_index/vector_stores/google/__init__.py
llama_index/vector_stores/google/base.py
llama_index/vector_stores/google/genai_extension.py
llama_index_vector_stores_google-0.4.1.dist-info/METADATA
llama_index_vector_stores_google-0.4.1.dist-info/WHEEL
llama_index_vector_stores_google-0.4.1.dist-info/licenses/LICENSE
llama_index_vector_stores_google-0.4.1.dist-info/RECORD
